jazzy_fish/__init__.py
jazzy_fish/encoder.py
jazzy_fish/generator.py
jazzy_fish/resources/01234_f233650/adjective.txt
jazzy_fish/resources/01234_f233650/adverb.txt
jazzy_fish/resources/01234_f233650/checksums.sha1
jazzy_fish/resources/01234_f233650/noun.txt
jazzy_fish/resources/01234_f233650/stats_2.txt
jazzy_fish/resources/01234_f233650/stats_3.txt
jazzy_fish/resources/01234_f233650/stats_4.txt
jazzy_fish/resources/01234_f233650/verb.txt
jazzy_fish/resources/012_8562fb9/adjective.txt
jazzy_fish/resources/012_8562fb9/adverb.txt
jazzy_fish/resources/012_8562fb9/checksums.sha1
jazzy_fish/resources/012_8562fb9/noun.txt
jazzy_fish/resources/012_8562fb9/stats_2.txt
jazzy_fish/resources/012_8562fb9/stats_3.txt
jazzy_fish/resources/012_8562fb9/stats_4.txt
jazzy_fish/resources/012_8562fb9/verb.txt
jazzy_fish/resources/024_84f184f/adjective.txt
jazzy_fish/resources/024_84f184f/adverb.txt
jazzy_fish/resources/024_84f184f/checksums.sha1
jazzy_fish/resources/024_84f184f/noun.txt
jazzy_fish/resources/024_84f184f/stats_2.txt
jazzy_fish/resources/024_84f184f/stats_3.txt
jazzy_fish/resources/024_84f184f/stats_4.txt
jazzy_fish/resources/024_84f184f/verb.txt
jazzy_fish_tools/__init__.py 
jazzy_fish_tools/clean_dictionary.py
jazzy_fish_tools/generate_wordlists.py
jazzy_fish_tools/helpers.py
jazzy_fish_tools/resources/ignored.txt
jazzy_fish_tools/resources/ignored_NOTICE.txt
jazzy_fish_tools/resources/process/ct_words.sql
jazzy_fish_tools/resources/process/process_words.sql
jazzy_fish-0.2.7.dist-info/METADATA
jazzy_fish-0.2.7.dist-info/WHEEL
jazzy_fish-0.2.7.dist-info/entry_points.txt
jazzy_fish-0.2.7.dist-info/RECORD
