Metadata-Version: 2.3
Name: jazzy_fish
Version: 0.2.7
Summary: Generate sufficiently-large, unique, human-friendly identifiers, represented as English-language phrases.
Project-URL: Bug reports, https://github.com/jazzy-fish/jazzy-fish/issues/new
Project-URL: Documentation, https://github.com/jazzy-fish/jazzy-fish/blob/main/python/README.md
Project-URL: Source, https://github.com/jazzy-fish/jazzy-fish
Author-email: Mihai Bojin <557584+MihaiBojin@users.noreply.github.com>
License-Expression: Apache-2.0
Keywords: decoder,encoder,human-friendly,identifiers,jazzyfish,unique
Classifier: Development Status :: 4 - Beta
Classifier: Intended Audience :: Developers
Classifier: License :: OSI Approved :: Apache Software License
Classifier: Natural Language :: English
Classifier: Programming Language :: Python :: 3
Classifier: Programming Language :: Python :: 3.9
Classifier: Programming Language :: Python :: 3.10
Classifier: Programming Language :: Python :: 3.11
Classifier: Programming Language :: Python :: 3.12
Requires-Python: >=3.9
Provides-Extra: cli
Requires-Dist: duckdb==1.0.0; extra == 'cli'
Provides-Extra: dev
Requires-Dist: build==1.2.1; extra == 'dev'
Requires-Dist: pre-commit==3.7.1; extra == 'dev'
Requires-Dist: pytest==8.2.2; extra == 'dev'
Requires-Dist: toml==0.10.2; extra == 'dev'
Requires-Dist: twine==5.1.1; extra == 'dev'
Requires-Dist: wheel-inspect==1.7.1; extra == 'dev'
Requires-Dist: wheel==0.43.0; extra == 'dev'
